README.md
setup.cfg
setup.py
web3automatization/__init__.py
web3automatization/requirements.txt
web3automatization/wallets.txt
web3automatization.egg-info/PKG-INFO
web3automatization.egg-info/SOURCES.txt
web3automatization.egg-info/dependency_links.txt
web3automatization.egg-info/requires.txt
web3automatization.egg-info/top_level.txt
web3automatization/__pycache__/__init__.cpython-312.pyc
web3automatization/abi/ERC20.json
web3automatization/abi/abis.py
web3automatization/abi/crosscurve_start.json
web3automatization/abi/iotex_TokenCashierWithPayload.json
web3automatization/abi/uniswap_quoter.json
web3automatization/abi/uniswap_router.json
web3automatization/abi/__pycache__/abis.cpython-312.pyc
web3automatization/classes/chain.py
web3automatization/classes/client.py
web3automatization/classes/__pycache__/chain.cpython-312.pyc
web3automatization/classes/__pycache__/client.cpython-312.pyc
web3automatization/db/config.py
web3automatization/db/logic.py
web3automatization/modules/crosscurve/config.py
web3automatization/modules/crosscurve/logic.py
web3automatization/modules/crosscurve/usage_example.py
web3automatization/modules/crosscurve/__pycache__/config.cpython-312.pyc
web3automatization/modules/crosscurve/__pycache__/logic.cpython-312.pyc
web3automatization/modules/iotex/config.py
web3automatization/modules/iotex/logic.py
web3automatization/modules/iotex/usage_example.py
web3automatization/modules/iotex/__pycache__/config.cpython-312.pyc
web3automatization/modules/iotex/__pycache__/logic.cpython-312.pyc
web3automatization/modules/uniswap/config.py
web3automatization/modules/uniswap/logic.py
web3automatization/modules/uniswap/usage_example.py
web3automatization/utils/generate_account.py
web3automatization/utils/read_utils.py
web3automatization/utils/__pycache__/generate_account.cpython-312.pyc
web3automatization/utils/__pycache__/read_utils.cpython-312.pyc