Metadata-Version: 2.1
Name: web3automatization
Version: 0.0.8
Summary: A library for simplified interaction with web3.From sybils for sybils.
Home-page: https://github.com/g7AzaZLO/web3automatization
Download-URL: https://github.com/g7AzaZLO/web3automatization/archive/v0.0.8.zip
Author: G7[azazlo]
Author-email: MaloyMeee@yandex.ru
License: Apache Licence, Version 2.0
Requires-Dist: web3==7.4.0
Requires-Dist: hexbytes==1.2.1
Requires-Dist: requests==2.32.3
Requires-Dist: aiosqlite==0.20.0
